{
	"Generated": "2026-06-01T03:46:22.182Z",
	"Mode": "module",
	"GitHubOrg": "fable-retold",
	"DefaultBranch": "master",
	"Module": {
		"Name": "pict-renderer-graph",
		"Repo": "pict-renderer-graph",
		"Group": "",
		"Branch": "master",
		"HasDocs": true,
		"HasCover": true,
		"Sidebar": [
			{
				"Title": "Getting Started",
				"Children": [
					{
						"Title": "Overview",
						"Path": "README.md"
					},
					{
						"Title": "Quick Start",
						"Path": "quickstart.md"
					}
				]
			},
			{
				"Title": "Guide",
				"Children": [
					{
						"Title": "Architecture",
						"Path": "architecture.md"
					},
					{
						"Title": "Diagram Types",
						"Path": "diagram-types.md"
					},
					{
						"Title": "Styles",
						"Path": "styles.md"
					},
					{
						"Title": "Invocation Modes",
						"Path": "invocation-modes.md"
					}
				]
			},
			{
				"Title": "Retold Ecosystem",
				"Children": [
					{
						"Title": "pict-section-excalidraw",
						"Path": "https://fable-retold.github.io/pict-section-excalidraw/README.md"
					},
					{
						"Title": "Fable",
						"Path": "https://fable-retold.github.io/fable/README.md"
					},
					{
						"Title": "fable-serviceproviderbase",
						"Path": "https://fable-retold.github.io/fable-serviceproviderbase/README.md"
					},
					{
						"Title": "Orator",
						"Path": "https://fable-retold.github.io/orator/README.md"
					}
				]
			}
		],
		"DocFiles": [
			".nojekyll",
			"README.md",
			"_cover.md",
			"_sidebar.md",
			"_version.json",
			"architecture.md",
			"diagram-types.md",
			"index.html",
			"invocation-modes.md",
			"quickstart.md",
			"retold-catalog.json",
			"retold-keyword-index.json",
			"styles.md"
		]
	},
	"Groups": []
}